SMmultiio/__init__.py
SMmultiio/multiio_data.py
multiio/__init__.py
multiio/multiio_data.py
multiio-1.1.0.dist-info/METADATA
multiio-1.1.0.dist-info/WHEEL
multiio-1.1.0.dist-info/top_level.txt
multiio-1.1.0.dist-info/RECORD
